pytest_asyncio/__init__.py
pytest_asyncio/_version.py
pytest_asyncio/plugin.py
pytest_asyncio/py.typed
pytest_asyncio-0.23.8.dist-info/LICENSE
pytest_asyncio-0.23.8.dist-info/METADATA
pytest_asyncio-0.23.8.dist-info/WHEEL
pytest_asyncio-0.23.8.dist-info/entry_points.txt
pytest_asyncio-0.23.8.dist-info/top_level.txt
pytest_asyncio-0.23.8.dist-info/RECORD
