Metadata-Version: 2.1
Name: pytest-asyncio
Version: 0.23.8
Summary: Pytest support for asyncio
Home-page: https://github.com/pytest-dev/pytest-asyncio
Author: Tin Tvrtković <tinchester@gmail.com>
Author-email: tinchester@gmail.com
License: Apache 2.0
Project-URL: Documentation, https://pytest-asyncio.readthedocs.io
Project-URL: Changelog, https://pytest-asyncio.readthedocs.io/en/latest/reference/changelog.html
Project-URL: Source Code, https://github.com/pytest-dev/pytest-asyncio
Project-URL: Bug Tracker, https://github.com/pytest-dev/pytest-asyncio/issues
Classifier: Development Status :: 4 - Beta
Classifier: Intended Audience :: Developers
Classifier: License :: OSI Approved :: Apache Software License
Classifier: Programming Language :: Python :: 3.8
Classifier: Programming Language :: Python :: 3.9
Classifier: Programming Language :: Python :: 3.10
Classifier: Programming Language :: Python :: 3.11
Classifier: Programming Language :: Python :: 3.12
Classifier: Programming Language :: Python :: 3.13
Classifier: Topic :: Software Development :: Testing
Classifier: Framework :: AsyncIO
Classifier: Framework :: Pytest
Classifier: Typing :: Typed
Requires-Python: >=3.8
License-File: LICENSE
Requires-Dist: pytest<9,>=7.0.0
Provides-Extra: testing
Requires-Dist: coverage>=6.2; extra == "testing"
Requires-Dist: hypothesis>=5.7.1; extra == "testing"
Provides-Extra: docs
Requires-Dist: sphinx>=5.3; extra == "docs"
Requires-Dist: sphinx-rtd-theme>=1.0; extra == "docs"
